odoo10_addon_project_scrum-10.0.1.0.1-nspkg.pth
odoo/addons/project_scrum/README.rst
odoo/addons/project_scrum/__init__.py
odoo/addons/project_scrum/__manifest__.py
odoo/addons/project_scrum/data/project_scrum_test_task_view.xml
odoo/addons/project_scrum/data/sequences_projects.xml
odoo/addons/project_scrum/demo/project_scrum_demo.xml
odoo/addons/project_scrum/i18n/ar.po
odoo/addons/project_scrum/i18n/de.po
odoo/addons/project_scrum/i18n/en_US.po
odoo/addons/project_scrum/i18n/fi.po
odoo/addons/project_scrum/i18n/fr.po
odoo/addons/project_scrum/i18n/project_scrum.pot
odoo/addons/project_scrum/i18n/sv_SE.po
odoo/addons/project_scrum/models/__init__.py
odoo/addons/project_scrum/models/project_project.py
odoo/addons/project_scrum/models/project_scrum_actors.py
odoo/addons/project_scrum/models/project_scrum_meeting.py
odoo/addons/project_scrum/models/project_scrum_sprint.py
odoo/addons/project_scrum/models/project_scrum_test.py
odoo/addons/project_scrum/models/project_scrum_us.py
odoo/addons/project_scrum/models/project_task.py
odoo/addons/project_scrum/security/ir.model.access.csv
odoo/addons/project_scrum/security/project_security.xml
odoo/addons/project_scrum/security/res_groups.xml
odoo/addons/project_scrum/static/description/icon.png
odoo/addons/project_scrum/tests/__init__.py
odoo/addons/project_scrum/tests/test_project_scrum.py
odoo/addons/project_scrum/views/mail_template.xml
odoo/addons/project_scrum/views/menu.xml
odoo/addons/project_scrum/views/project_project.xml
odoo/addons/project_scrum/views/project_scrum_meeting.xml
odoo/addons/project_scrum/views/project_scrum_sprint.xml
odoo/addons/project_scrum/views/project_scrum_test.xml
odoo/addons/project_scrum/views/project_scrum_us.xml
odoo/addons/project_scrum/views/project_task.xml
odoo10_addon_project_scrum-10.0.1.0.1.dist-info/METADATA
odoo10_addon_project_scrum-10.0.1.0.1.dist-info/WHEEL
odoo10_addon_project_scrum-10.0.1.0.1.dist-info/namespace_packages.txt
odoo10_addon_project_scrum-10.0.1.0.1.dist-info/top_level.txt
odoo10_addon_project_scrum-10.0.1.0.1.dist-info/RECORD
