Metadata-Version: 2.1
Name: odoo10-addon-project-scrum
Version: 10.0.1.0.1
Summary: Use Scrum Method to manage your project
Home-page: https://github.com/OCA/project-agile
Author: Odoo Community Association (OCA)
Author-email: support@odoo-community.org
License: AGPL-3
Platform: UNKNOWN
Classifier: Programming Language :: Python
Classifier: Framework :: Odoo
Classifier: License :: OSI Approved :: GNU Affero General Public License v3
Requires-Python: ~=2.7
Requires-Dist: odoo10-addon-project-stage-state
Requires-Dist: odoo10-addon-project-task-code
Requires-Dist: odoo (<10.1dev,>=10.0)
